{
  "appInfo" : {
    "build" : "213.5744.223",
    "buildDate" : "2021-11-27T07:14:28.224Z[UTC]",
    "productCode" : "IC",
    "generated" : "2021-12-28T10:23:47.657135Z",
    "os" : "Linux 5.4.0-91-generic",
    "runtime" : "JetBrains s.r.o. 11.0.13 11.0.13+7-b1751.19"
  },
  "runtimeInfo" : {
    "maxMemory" : 536870912,
    "numberOfProcessors" : 8,
    "maxNumberOfIndexingThreads" : 4,
    "maxSizeOfFileForIntelliSense" : 2560000,
    "maxSizeOfFileForContentLoading" : 20971520
  },
  "projectIndexingHistory" : {
    "projectName" : "JBTestProject",
    "times" : {
      "indexingReason" : "On project open",
      "totalUpdatingTime" : 8353490466,
      "indexingTime" : 0,
      "contentLoadingTime" : 0,
      "scanFilesTime" : 8237734000,
      "pushPropertiesTime" : 1117000,
      "indexExtensionsTime" : 0,
      "updatingStart" : "2021-12-28T10:23:39.293977Z",
      "updatingEnd" : "2021-12-28T10:23:47.652859Z",
      "totalSuspendedTime" : 0,
      "wasInterrupted" : false
    },
    "fileCount" : {
      "numberOfFileProviders" : 23,
      "numberOfScannedFiles" : 33997,
      "numberOfFilesIndexedByInfrastructureExtensionsDuringScan" : 0,
      "numberOfFilesScheduledForIndexingAfterScan" : 0,
      "numberOfFilesIndexedByInfrastructureExtensionsDuringIndexingStage" : 0,
      "numberOfFilesIndexedWithLoadingContent" : 0
    },
    "totalStatsPerFileType" : [ ],
    "totalStatsPerIndexer" : [ ],
    "scanningStatistics" : [ {
      "providerName" : "JDK 11",
      "numberOfScannedFiles" : 31209,
      "numberOfSkippedFiles" : 0,
      "numberOfFilesForIndexing" : 0,
      "numberOfFilesFullyIndexedByInfrastructureExtensions" : 0,
      "scanningTime" : 5376285417,
      "timeProcessingUpToDateFiles" : 3055287629,
      "timeUpdatingContentLessIndexes" : 120947944,
      "timeIndexingWithoutContent" : 0
    }, {
      "providerName" : "Library Gradle: org.jetbrains.kotlin:kotlin-stdlib:1.6.10",
      "numberOfScannedFiles" : 1061,
      "numberOfSkippedFiles" : 0,
      "numberOfFilesForIndexing" : 0,
      "numberOfFilesFullyIndexedByInfrastructureExtensions" : 0,
      "scanningTime" : 1792883204,
      "timeProcessingUpToDateFiles" : 638482510,
      "timeUpdatingContentLessIndexes" : 17029719,
      "timeIndexingWithoutContent" : 0
    }, {
      "providerName" : "Library Gradle: org.jetbrains.kotlin:kotlin-test-junit5:1.6.10",
      "numberOfScannedFiles" : 11,
      "numberOfSkippedFiles" : 0,
      "numberOfFilesForIndexing" : 0,
      "numberOfFilesFullyIndexedByInfrastructureExtensions" : 0,
      "scanningTime" : 1303569359,
      "timeProcessingUpToDateFiles" : 22102196,
      "timeUpdatingContentLessIndexes" : 121677,
      "timeIndexingWithoutContent" : 0
    }, {
      "providerName" : "Library Gradle: org.jetbrains.kotlin:kotlin-stdlib-common:1.6.10",
      "numberOfScannedFiles" : 462,
      "numberOfSkippedFiles" : 0,
      "numberOfFilesForIndexing" : 0,
      "numberOfFilesFullyIndexedByInfrastructureExtensions" : 0,
      "scanningTime" : 1026480710,
      "timeProcessingUpToDateFiles" : 309315227,
      "timeUpdatingContentLessIndexes" : 6512822,
      "timeIndexingWithoutContent" : 0
    }, {
      "providerName" : "Library Gradle: org.junit.jupiter:junit-jupiter-api:5.6.0",
      "numberOfScannedFiles" : 266,
      "numberOfSkippedFiles" : 0,
      "numberOfFilesForIndexing" : 0,
      "numberOfFilesFullyIndexedByInfrastructureExtensions" : 0,
      "scanningTime" : 854228587,
      "timeProcessingUpToDateFiles" : 330117329,
      "timeUpdatingContentLessIndexes" : 4814104,
      "timeIndexingWithoutContent" : 0
    }, {
      "providerName" : "Library Gradle: org.jetbrains.kotlin:kotlin-test:1.6.10",
      "numberOfScannedFiles" : 106,
      "numberOfSkippedFiles" : 0,
      "numberOfFilesForIndexing" : 0,
      "numberOfFilesFullyIndexedByInfrastructureExtensions" : 0,
      "scanningTime" : 731958462,
      "timeProcessingUpToDateFiles" : 234545900,
      "timeUpdatingContentLessIndexes" : 8434303,
      "timeIndexingWithoutContent" : 0
    }, {
      "providerName" : "Library Gradle: org.junit.jupiter:junit-jupiter-engine:5.6.0",
      "numberOfScannedFiles" : 212,
      "numberOfSkippedFiles" : 0,
      "numberOfFilesForIndexing" : 0,
      "numberOfFilesFullyIndexedByInfrastructureExtensions" : 0,
      "scanningTime" : 630219801,
      "timeProcessingUpToDateFiles" : 255541122,
      "timeUpdatingContentLessIndexes" : 2863210,
      "timeIndexingWithoutContent" : 0
    }, {
      "providerName" : "Library Gradle: org.junit.platform:junit-platform-engine:1.6.0",
      "numberOfScannedFiles" : 222,
      "numberOfSkippedFiles" : 0,
      "numberOfFilesForIndexing" : 0,
      "numberOfFilesFullyIndexedByInfrastructureExtensions" : 0,
      "scanningTime" : 564172813,
      "timeProcessingUpToDateFiles" : 217724612,
      "timeUpdatingContentLessIndexes" : 2619766,
      "timeIndexingWithoutContent" : 0
    }, {
      "providerName" : "Indexable set contributor 'com.intellij.javaee.ExternalResourcesRootsProvider@717ae7e1' (non-project)",
      "numberOfScannedFiles" : 224,
      "numberOfSkippedFiles" : 4,
      "numberOfFilesForIndexing" : 0,
      "numberOfFilesFullyIndexedByInfrastructureExtensions" : 0,
      "scanningTime" : 477432575,
      "timeProcessingUpToDateFiles" : 137559667,
      "timeUpdatingContentLessIndexes" : 3629936,
      "timeIndexingWithoutContent" : 0
    }, {
      "providerName" : "Library Gradle: org.junit.platform:junit-platform-commons:1.6.0",
      "numberOfScannedFiles" : 87,
      "numberOfSkippedFiles" : 0,
      "numberOfFilesForIndexing" : 0,
      "numberOfFilesFullyIndexedByInfrastructureExtensions" : 0,
      "scanningTime" : 435966231,
      "timeProcessingUpToDateFiles" : 152859480,
      "timeUpdatingContentLessIndexes" : 9401113,
      "timeIndexingWithoutContent" : 0
    }, {
      "providerName" : "Library Gradle: org.jetbrains:annotations:13.0",
      "numberOfScannedFiles" : 52,
      "numberOfSkippedFiles" : 0,
      "numberOfFilesForIndexing" : 0,
      "numberOfFilesFullyIndexedByInfrastructureExtensions" : 0,
      "scanningTime" : 401234751,
      "timeProcessingUpToDateFiles" : 144093899,
      "timeUpdatingContentLessIndexes" : 1943109,
      "timeIndexingWithoutContent" : 0
    }, {
      "providerName" : "Library Gradle: org.jetbrains.kotlin:kotlin-stdlib-jdk8:1.6.10",
      "numberOfScannedFiles" : 22,
      "numberOfSkippedFiles" : 0,
      "numberOfFilesForIndexing" : 0,
      "numberOfFilesFullyIndexedByInfrastructureExtensions" : 0,
      "scanningTime" : 306002570,
      "timeProcessingUpToDateFiles" : 41513913,
      "timeUpdatingContentLessIndexes" : 794616,
      "timeIndexingWithoutContent" : 0
    }, {
      "providerName" : "Library Gradle: org.jetbrains.kotlin:kotlin-stdlib-jdk7:1.6.10",
      "numberOfScannedFiles" : 16,
      "numberOfSkippedFiles" : 0,
      "numberOfFilesForIndexing" : 0,
      "numberOfFilesFullyIndexedByInfrastructureExtensions" : 0,
      "scanningTime" : 289107133,
      "timeProcessingUpToDateFiles" : 53193546,
      "timeUpdatingContentLessIndexes" : 645167,
      "timeIndexingWithoutContent" : 0
    }, {
      "providerName" : "Module 'JBTestProject' (JBTestProject)",
      "numberOfScannedFiles" : 19,
      "numberOfSkippedFiles" : 0,
      "numberOfFilesForIndexing" : 0,
      "numberOfFilesFullyIndexedByInfrastructureExtensions" : 0,
      "scanningTime" : 150058035,
      "timeProcessingUpToDateFiles" : 21027061,
      "timeUpdatingContentLessIndexes" : 2657415,
      "timeIndexingWithoutContent" : 0
    }, {
      "providerName" : "Module 'JBTestProject.main' (main)",
      "numberOfScannedFiles" : 5,
      "numberOfSkippedFiles" : 0,
      "numberOfFilesForIndexing" : 0,
      "numberOfFilesFullyIndexedByInfrastructureExtensions" : 0,
      "scanningTime" : 112434720,
      "timeProcessingUpToDateFiles" : 4219587,
      "timeUpdatingContentLessIndexes" : 225310,
      "timeIndexingWithoutContent" : 0
    }, {
      "providerName" : "Library Gradle: org.opentest4j:opentest4j:1.2.0",
      "numberOfScannedFiles" : 16,
      "numberOfSkippedFiles" : 0,
      "numberOfFilesForIndexing" : 0,
      "numberOfFilesFullyIndexedByInfrastructureExtensions" : 0,
      "scanningTime" : 67055693,
      "timeProcessingUpToDateFiles" : 43827768,
      "timeUpdatingContentLessIndexes" : 380586,
      "timeIndexingWithoutContent" : 0
    }, {
      "providerName" : "Library Gradle: org.apiguardian:apiguardian-api:1.1.0",
      "numberOfScannedFiles" : 6,
      "numberOfSkippedFiles" : 0,
      "numberOfFilesForIndexing" : 0,
      "numberOfFilesFullyIndexedByInfrastructureExtensions" : 0,
      "scanningTime" : 27392676,
      "timeProcessingUpToDateFiles" : 16392323,
      "timeUpdatingContentLessIndexes" : 142403,
      "timeIndexingWithoutContent" : 0
    }, {
      "providerName" : "Indexable set contributor 'Scratches & Consoles' (non-project)",
      "numberOfScannedFiles" : 1,
      "numberOfSkippedFiles" : 0,
      "numberOfFilesForIndexing" : 0,
      "numberOfFilesFullyIndexedByInfrastructureExtensions" : 0,
      "scanningTime" : 18612408,
      "timeProcessingUpToDateFiles" : 44616,
      "timeUpdatingContentLessIndexes" : 24952,
      "timeIndexingWithoutContent" : 0
    }, {
      "providerName" : "Module 'JBTestProject.test' (test)",
      "numberOfScannedFiles" : 0,
      "numberOfSkippedFiles" : 0,
      "numberOfFilesForIndexing" : 0,
      "numberOfFilesFullyIndexedByInfrastructureExtensions" : 0,
      "scanningTime" : 0,
      "timeProcessingUpToDateFiles" : 0,
      "timeUpdatingContentLessIndexes" : 0,
      "timeIndexingWithoutContent" : 0
    }, {
      "providerName" : "Indexable set contributor 'Scratches & Consoles' (project)",
      "numberOfScannedFiles" : 0,
      "numberOfSkippedFiles" : 0,
      "numberOfFilesForIndexing" : 0,
      "numberOfFilesFullyIndexedByInfrastructureExtensions" : 0,
      "scanningTime" : 0,
      "timeProcessingUpToDateFiles" : 0,
      "timeUpdatingContentLessIndexes" : 0,
      "timeIndexingWithoutContent" : 0
    }, {
      "providerName" : "Indexable set contributor 'com.intellij.javaee.ExternalResourcesRootsProvider@717ae7e1' (project)",
      "numberOfScannedFiles" : 0,
      "numberOfSkippedFiles" : 0,
      "numberOfFilesForIndexing" : 0,
      "numberOfFilesFullyIndexedByInfrastructureExtensions" : 0,
      "scanningTime" : 0,
      "timeProcessingUpToDateFiles" : 0,
      "timeUpdatingContentLessIndexes" : 0,
      "timeIndexingWithoutContent" : 0
    }, {
      "providerName" : "Indexable set contributor 'Kotlin Script dependencies' (project)",
      "numberOfScannedFiles" : 0,
      "numberOfSkippedFiles" : 0,
      "numberOfFilesForIndexing" : 0,
      "numberOfFilesFullyIndexedByInfrastructureExtensions" : 0,
      "scanningTime" : 0,
      "timeProcessingUpToDateFiles" : 0,
      "timeUpdatingContentLessIndexes" : 0,
      "timeIndexingWithoutContent" : 0
    }, {
      "providerName" : "Indexable set contributor 'Kotlin Script dependencies' (non-project)",
      "numberOfScannedFiles" : 0,
      "numberOfSkippedFiles" : 0,
      "numberOfFilesForIndexing" : 0,
      "numberOfFilesFullyIndexedByInfrastructureExtensions" : 0,
      "scanningTime" : 0,
      "timeProcessingUpToDateFiles" : 0,
      "timeUpdatingContentLessIndexes" : 0,
      "timeIndexingWithoutContent" : 0
    } ],
    "fileProviderStatistics" : [ ]
  }
}