{
  "appInfo" : {
    "build" : "213.5744.223",
    "buildDate" : "2021-11-27T07:14:31.5Z[UTC]",
    "productCode" : "IC",
    "generated" : "2021-12-27T14:15:51.73862Z",
    "os" : "Linux 5.4.0-91-generic",
    "runtime" : "JetBrains s.r.o. 11.0.13 11.0.13+7-b1751.19"
  },
  "runtimeInfo" : {
    "maxMemory" : 536870912,
    "numberOfProcessors" : 8,
    "maxNumberOfIndexingThreads" : 4,
    "maxSizeOfFileForIntelliSense" : 2560000,
    "maxSizeOfFileForContentLoading" : 20971520
  },
  "projectIndexingHistory" : {
    "projectName" : "JBTestProject",
    "times" : {
      "indexingReason" : "On project open",
      "totalUpdatingTime" : 7355637428,
      "indexingTime" : 228369000,
      "contentLoadingTime" : 2368754,
      "scanFilesTime" : 6853913000,
      "pushPropertiesTime" : 1115000,
      "indexExtensionsTime" : 0,
      "updatingStart" : "2021-12-27T14:15:44.373325Z",
      "updatingEnd" : "2021-12-27T14:15:51.733481Z",
      "totalSuspendedTime" : 0,
      "wasInterrupted" : false
    },
    "fileCount" : {
      "numberOfFileProviders" : 23,
      "numberOfScannedFiles" : 33995,
      "numberOfFilesIndexedByInfrastructureExtensionsDuringScan" : 0,
      "numberOfFilesScheduledForIndexingAfterScan" : 1,
      "numberOfFilesIndexedByInfrastructureExtensionsDuringIndexingStage" : 0,
      "numberOfFilesIndexedWithLoadingContent" : 1
    },
    "totalStatsPerFileType" : [ {
      "fileType" : "textmate",
      "partOfTotalProcessingTime" : {
        "part" : 179845730,
        "total" : 179845730
      },
      "partOfTotalContentLoadingTime" : {
        "part" : 2232990,
        "total" : 2232990
      },
      "totalNumberOfFiles" : 1,
      "totalFilesSize" : 2763,
      "indexingSpeed" : {
        "totalBytes" : 2763,
        "totalTime" : 179845730
      },
      "biggestContributors" : [ {
        "providerName" : "Module 'JBTestProject' (JBTestProject)",
        "numberOfFiles" : 1,
        "totalFilesSize" : 2763,
        "partOfTotalProcessingTimeOfThisFileType" : {
          "part" : 179845730,
          "total" : 179845730
        }
      } ]
    } ],
    "totalStatsPerIndexer" : [ {
      "indexId" : "TodoIndex",
      "partOfTotalIndexingTime" : {
        "part" : 36573646,
        "total" : 52580197
      },
      "totalNumberOfFiles" : 1,
      "totalNumberOfFilesIndexedByExtensions" : 0,
      "totalFilesSize" : 2763,
      "indexingSpeed" : {
        "totalBytes" : 2763,
        "totalTime" : 36573646
      },
      "snapshotInputMappingStats" : {
        "totalRequests" : 0,
        "totalMisses" : 0,
        "totalHits" : 0
      }
    }, {
      "indexId" : "IdIndex",
      "partOfTotalIndexingTime" : {
        "part" : 10150548,
        "total" : 52580197
      },
      "totalNumberOfFiles" : 1,
      "totalNumberOfFilesIndexedByExtensions" : 0,
      "totalFilesSize" : 2763,
      "indexingSpeed" : {
        "totalBytes" : 2763,
        "totalTime" : 10150548
      },
      "snapshotInputMappingStats" : {
        "totalRequests" : 0,
        "totalMisses" : 0,
        "totalHits" : 0
      }
    }, {
      "indexId" : "Trigram.Index",
      "partOfTotalIndexingTime" : {
        "part" : 5838283,
        "total" : 52580197
      },
      "totalNumberOfFiles" : 1,
      "totalNumberOfFilesIndexedByExtensions" : 0,
      "totalFilesSize" : 2763,
      "indexingSpeed" : {
        "totalBytes" : 2763,
        "totalTime" : 5838283
      },
      "snapshotInputMappingStats" : {
        "totalRequests" : 0,
        "totalMisses" : 0,
        "totalHits" : 0
      }
    }, {
      "indexId" : "filetypes",
      "partOfTotalIndexingTime" : {
        "part" : 17720,
        "total" : 52580197
      },
      "totalNumberOfFiles" : 1,
      "totalNumberOfFilesIndexedByExtensions" : 0,
      "totalFilesSize" : 2763,
      "indexingSpeed" : {
        "totalBytes" : 2763,
        "totalTime" : 17720
      },
      "snapshotInputMappingStats" : {
        "totalRequests" : 0,
        "totalMisses" : 0,
        "totalHits" : 0
      }
    } ],
    "scanningStatistics" : [ {
      "providerName" : "JDK 11",
      "numberOfScannedFiles" : 31209,
      "numberOfSkippedFiles" : 0,
      "numberOfFilesForIndexing" : 0,
      "numberOfFilesFullyIndexedByInfrastructureExtensions" : 0,
      "scanningTime" : 3365665406,
      "timeProcessingUpToDateFiles" : 591600698,
      "timeUpdatingContentLessIndexes" : 98344659,
      "timeIndexingWithoutContent" : 0
    }, {
      "providerName" : "Library Gradle: org.jetbrains.kotlin:kotlin-stdlib:1.6.10",
      "numberOfScannedFiles" : 1061,
      "numberOfSkippedFiles" : 0,
      "numberOfFilesForIndexing" : 0,
      "numberOfFilesFullyIndexedByInfrastructureExtensions" : 0,
      "scanningTime" : 1065179516,
      "timeProcessingUpToDateFiles" : 230711538,
      "timeUpdatingContentLessIndexes" : 17016431,
      "timeIndexingWithoutContent" : 0
    }, {
      "providerName" : "Library Gradle: org.jetbrains.kotlin:kotlin-test-junit5:1.6.10",
      "numberOfScannedFiles" : 11,
      "numberOfSkippedFiles" : 0,
      "numberOfFilesForIndexing" : 0,
      "numberOfFilesFullyIndexedByInfrastructureExtensions" : 0,
      "scanningTime" : 1024803479,
      "timeProcessingUpToDateFiles" : 2644016,
      "timeUpdatingContentLessIndexes" : 187521,
      "timeIndexingWithoutContent" : 0
    }, {
      "providerName" : "Library Gradle: org.jetbrains.kotlin:kotlin-test:1.6.10",
      "numberOfScannedFiles" : 106,
      "numberOfSkippedFiles" : 0,
      "numberOfFilesForIndexing" : 0,
      "numberOfFilesFullyIndexedByInfrastructureExtensions" : 0,
      "scanningTime" : 565834381,
      "timeProcessingUpToDateFiles" : 127616073,
      "timeUpdatingContentLessIndexes" : 3170743,
      "timeIndexingWithoutContent" : 0
    }, {
      "providerName" : "Library Gradle: org.jetbrains.kotlin:kotlin-stdlib-common:1.6.10",
      "numberOfScannedFiles" : 462,
      "numberOfSkippedFiles" : 0,
      "numberOfFilesForIndexing" : 0,
      "numberOfFilesFullyIndexedByInfrastructureExtensions" : 0,
      "scanningTime" : 545909608,
      "timeProcessingUpToDateFiles" : 93338670,
      "timeUpdatingContentLessIndexes" : 14826084,
      "timeIndexingWithoutContent" : 0
    }, {
      "providerName" : "Library Gradle: org.junit.jupiter:junit-jupiter-api:5.6.0",
      "numberOfScannedFiles" : 266,
      "numberOfSkippedFiles" : 0,
      "numberOfFilesForIndexing" : 0,
      "numberOfFilesFullyIndexedByInfrastructureExtensions" : 0,
      "scanningTime" : 517928415,
      "timeProcessingUpToDateFiles" : 162153816,
      "timeUpdatingContentLessIndexes" : 3752914,
      "timeIndexingWithoutContent" : 0
    }, {
      "providerName" : "Library Gradle: org.jetbrains:annotations:13.0",
      "numberOfScannedFiles" : 52,
      "numberOfSkippedFiles" : 0,
      "numberOfFilesForIndexing" : 0,
      "numberOfFilesFullyIndexedByInfrastructureExtensions" : 0,
      "scanningTime" : 361864658,
      "timeProcessingUpToDateFiles" : 88185213,
      "timeUpdatingContentLessIndexes" : 2194393,
      "timeIndexingWithoutContent" : 0
    }, {
      "providerName" : "Module 'JBTestProject' (JBTestProject)",
      "numberOfScannedFiles" : 19,
      "numberOfSkippedFiles" : 0,
      "numberOfFilesForIndexing" : 1,
      "numberOfFilesFullyIndexedByInfrastructureExtensions" : 0,
      "scanningTime" : 319076621,
      "timeProcessingUpToDateFiles" : 2965733,
      "timeUpdatingContentLessIndexes" : 55225286,
      "timeIndexingWithoutContent" : 0
    }, {
      "providerName" : "Library Gradle: org.jetbrains.kotlin:kotlin-stdlib-jdk7:1.6.10",
      "numberOfScannedFiles" : 16,
      "numberOfSkippedFiles" : 0,
      "numberOfFilesForIndexing" : 0,
      "numberOfFilesFullyIndexedByInfrastructureExtensions" : 0,
      "scanningTime" : 289020685,
      "timeProcessingUpToDateFiles" : 31041244,
      "timeUpdatingContentLessIndexes" : 806461,
      "timeIndexingWithoutContent" : 0
    }, {
      "providerName" : "Library Gradle: org.junit.platform:junit-platform-engine:1.6.0",
      "numberOfScannedFiles" : 222,
      "numberOfSkippedFiles" : 0,
      "numberOfFilesForIndexing" : 0,
      "numberOfFilesFullyIndexedByInfrastructureExtensions" : 0,
      "scanningTime" : 277352453,
      "timeProcessingUpToDateFiles" : 110477637,
      "timeUpdatingContentLessIndexes" : 6978018,
      "timeIndexingWithoutContent" : 0
    }, {
      "providerName" : "Library Gradle: org.jetbrains.kotlin:kotlin-stdlib-jdk8:1.6.10",
      "numberOfScannedFiles" : 22,
      "numberOfSkippedFiles" : 0,
      "numberOfFilesForIndexing" : 0,
      "numberOfFilesFullyIndexedByInfrastructureExtensions" : 0,
      "scanningTime" : 256267112,
      "timeProcessingUpToDateFiles" : 43339866,
      "timeUpdatingContentLessIndexes" : 1010949,
      "timeIndexingWithoutContent" : 0
    }, {
      "providerName" : "Library Gradle: org.junit.jupiter:junit-jupiter-engine:5.6.0",
      "numberOfScannedFiles" : 212,
      "numberOfSkippedFiles" : 0,
      "numberOfFilesForIndexing" : 0,
      "numberOfFilesFullyIndexedByInfrastructureExtensions" : 0,
      "scanningTime" : 248327175,
      "timeProcessingUpToDateFiles" : 82491556,
      "timeUpdatingContentLessIndexes" : 8384470,
      "timeIndexingWithoutContent" : 0
    }, {
      "providerName" : "Library Gradle: org.junit.platform:junit-platform-commons:1.6.0",
      "numberOfScannedFiles" : 87,
      "numberOfSkippedFiles" : 0,
      "numberOfFilesForIndexing" : 0,
      "numberOfFilesFullyIndexedByInfrastructureExtensions" : 0,
      "scanningTime" : 221794243,
      "timeProcessingUpToDateFiles" : 51097071,
      "timeUpdatingContentLessIndexes" : 1895339,
      "timeIndexingWithoutContent" : 0
    }, {
      "providerName" : "Indexable set contributor 'com.intellij.javaee.ExternalResourcesRootsProvider@275baa18' (non-project)",
      "numberOfScannedFiles" : 224,
      "numberOfSkippedFiles" : 4,
      "numberOfFilesForIndexing" : 0,
      "numberOfFilesFullyIndexedByInfrastructureExtensions" : 0,
      "scanningTime" : 213089765,
      "timeProcessingUpToDateFiles" : 63190367,
      "timeUpdatingContentLessIndexes" : 3178593,
      "timeIndexingWithoutContent" : 0
    }, {
      "providerName" : "Module 'JBTestProject.main' (main)",
      "numberOfScannedFiles" : 3,
      "numberOfSkippedFiles" : 0,
      "numberOfFilesForIndexing" : 0,
      "numberOfFilesFullyIndexedByInfrastructureExtensions" : 0,
      "scanningTime" : 112095314,
      "timeProcessingUpToDateFiles" : 4445133,
      "timeUpdatingContentLessIndexes" : 119975,
      "timeIndexingWithoutContent" : 0
    }, {
      "providerName" : "Library Gradle: org.opentest4j:opentest4j:1.2.0",
      "numberOfScannedFiles" : 16,
      "numberOfSkippedFiles" : 0,
      "numberOfFilesForIndexing" : 0,
      "numberOfFilesFullyIndexedByInfrastructureExtensions" : 0,
      "scanningTime" : 43683175,
      "timeProcessingUpToDateFiles" : 18183228,
      "timeUpdatingContentLessIndexes" : 289155,
      "timeIndexingWithoutContent" : 0
    }, {
      "providerName" : "Library Gradle: org.apiguardian:apiguardian-api:1.1.0",
      "numberOfScannedFiles" : 6,
      "numberOfSkippedFiles" : 0,
      "numberOfFilesForIndexing" : 0,
      "numberOfFilesFullyIndexedByInfrastructureExtensions" : 0,
      "scanningTime" : 25571832,
      "timeProcessingUpToDateFiles" : 2903898,
      "timeUpdatingContentLessIndexes" : 160015,
      "timeIndexingWithoutContent" : 0
    }, {
      "providerName" : "Indexable set contributor 'Scratches & Consoles' (non-project)",
      "numberOfScannedFiles" : 1,
      "numberOfSkippedFiles" : 0,
      "numberOfFilesForIndexing" : 0,
      "numberOfFilesFullyIndexedByInfrastructureExtensions" : 0,
      "scanningTime" : 21456266,
      "timeProcessingUpToDateFiles" : 25268,
      "timeUpdatingContentLessIndexes" : 11096,
      "timeIndexingWithoutContent" : 0
    }, {
      "providerName" : "Module 'JBTestProject.test' (test)",
      "numberOfScannedFiles" : 0,
      "numberOfSkippedFiles" : 0,
      "numberOfFilesForIndexing" : 0,
      "numberOfFilesFullyIndexedByInfrastructureExtensions" : 0,
      "scanningTime" : 0,
      "timeProcessingUpToDateFiles" : 0,
      "timeUpdatingContentLessIndexes" : 0,
      "timeIndexingWithoutContent" : 0
    }, {
      "providerName" : "Indexable set contributor 'Scratches & Consoles' (project)",
      "numberOfScannedFiles" : 0,
      "numberOfSkippedFiles" : 0,
      "numberOfFilesForIndexing" : 0,
      "numberOfFilesFullyIndexedByInfrastructureExtensions" : 0,
      "scanningTime" : 0,
      "timeProcessingUpToDateFiles" : 0,
      "timeUpdatingContentLessIndexes" : 0,
      "timeIndexingWithoutContent" : 0
    }, {
      "providerName" : "Indexable set contributor 'com.intellij.javaee.ExternalResourcesRootsProvider@275baa18' (project)",
      "numberOfScannedFiles" : 0,
      "numberOfSkippedFiles" : 0,
      "numberOfFilesForIndexing" : 0,
      "numberOfFilesFullyIndexedByInfrastructureExtensions" : 0,
      "scanningTime" : 0,
      "timeProcessingUpToDateFiles" : 0,
      "timeUpdatingContentLessIndexes" : 0,
      "timeIndexingWithoutContent" : 0
    }, {
      "providerName" : "Indexable set contributor 'Kotlin Script dependencies' (project)",
      "numberOfScannedFiles" : 0,
      "numberOfSkippedFiles" : 0,
      "numberOfFilesForIndexing" : 0,
      "numberOfFilesFullyIndexedByInfrastructureExtensions" : 0,
      "scanningTime" : 0,
      "timeProcessingUpToDateFiles" : 0,
      "timeUpdatingContentLessIndexes" : 0,
      "timeIndexingWithoutContent" : 0
    }, {
      "providerName" : "Indexable set contributor 'Kotlin Script dependencies' (non-project)",
      "numberOfScannedFiles" : 0,
      "numberOfSkippedFiles" : 0,
      "numberOfFilesForIndexing" : 0,
      "numberOfFilesFullyIndexedByInfrastructureExtensions" : 0,
      "scanningTime" : 0,
      "timeProcessingUpToDateFiles" : 0,
      "timeUpdatingContentLessIndexes" : 0,
      "timeIndexingWithoutContent" : 0
    } ],
    "fileProviderStatistics" : [ {
      "providerName" : "Module 'JBTestProject' (JBTestProject)",
      "totalNumberOfIndexedFiles" : 1,
      "totalNumberOfFilesFullyIndexedByExtensions" : 0,
      "totalIndexingTime" : 190780280,
      "contentLoadingTime" : 2368754,
      "numberOfTooLargeForIndexingFiles" : 0,
      "slowIndexedFiles" : [ ]
    } ]
  }
}