{
  "appInfo" : {
    "build" : "213.5744.223",
    "buildDate" : "2021-11-27T07:14:14.341Z[UTC]",
    "productCode" : "IC",
    "generated" : "2022-01-06T14:42:37.698119Z",
    "os" : "Linux 5.4.0-92-generic",
    "runtime" : "JetBrains s.r.o. 11.0.13 11.0.13+7-b1751.19"
  },
  "runtimeInfo" : {
    "maxMemory" : 536870912,
    "numberOfProcessors" : 8,
    "maxNumberOfIndexingThreads" : 4,
    "maxSizeOfFileForIntelliSense" : 2560000,
    "maxSizeOfFileForContentLoading" : 20971520
  },
  "projectIndexingHistory" : {
    "projectName" : "JBTestProject",
    "times" : {
      "indexingReason" : "On refresh of 83 files",
      "totalUpdatingTime" : 78762729,
      "indexingTime" : 63678000,
      "contentLoadingTime" : 13278227,
      "scanFilesTime" : 1551753,
      "pushPropertiesTime" : 0,
      "indexExtensionsTime" : 0,
      "updatingStart" : "2022-01-06T14:42:35.975186Z",
      "updatingEnd" : "2022-01-06T14:42:36.053943Z",
      "totalSuspendedTime" : 0,
      "wasInterrupted" : false
    },
    "fileCount" : {
      "numberOfFileProviders" : 1,
      "numberOfScannedFiles" : 83,
      "numberOfFilesIndexedByInfrastructureExtensionsDuringScan" : 0,
      "numberOfFilesScheduledForIndexingAfterScan" : 83,
      "numberOfFilesIndexedByInfrastructureExtensionsDuringIndexingStage" : 0,
      "numberOfFilesIndexedWithLoadingContent" : 83
    },
    "totalStatsPerFileType" : [ {
      "fileType" : "UNKNOWN",
      "partOfTotalProcessingTime" : {
        "part" : 218077051,
        "total" : 218077051
      },
      "partOfTotalContentLoadingTime" : {
        "part" : 45537731,
        "total" : 45537731
      },
      "totalNumberOfFiles" : 83,
      "totalFilesSize" : 0,
      "indexingSpeed" : {
        "totalBytes" : 0,
        "totalTime" : 218077051
      },
      "biggestContributors" : [ {
        "providerName" : "Refreshed files",
        "numberOfFiles" : 83,
        "totalFilesSize" : 0,
        "partOfTotalProcessingTimeOfThisFileType" : {
          "part" : 218077051,
          "total" : 218077051
        }
      } ]
    } ],
    "totalStatsPerIndexer" : [ ],
    "scanningStatistics" : [ {
      "providerName" : "Refreshed files",
      "numberOfScannedFiles" : 83,
      "numberOfSkippedFiles" : 0,
      "numberOfFilesForIndexing" : 83,
      "numberOfFilesFullyIndexedByInfrastructureExtensions" : 0,
      "scanningTime" : 1551753,
      "timeProcessingUpToDateFiles" : 0,
      "timeUpdatingContentLessIndexes" : 0,
      "timeIndexingWithoutContent" : 0
    } ],
    "fileProviderStatistics" : [ {
      "providerName" : "Refreshed files",
      "totalNumberOfIndexedFiles" : 83,
      "totalNumberOfFilesFullyIndexedByExtensions" : 0,
      "totalIndexingTime" : 63588516,
      "contentLoadingTime" : 13278227,
      "numberOfTooLargeForIndexingFiles" : 0,
      "slowIndexedFiles" : [ ]
    } ]
  }
}